aws_utilities/ApiGateway.py
aws_utilities/AwsApiReports.py
aws_utilities/Lambda.py
aws_utilities/S3.py
aws_utilities/__init__.py
aws_utilities/aws_base.py
aws_utilities/aws_utilities.py
aws_utilities/ses.py
py_aws_utilities-0.0.3.dist-info/LICENSE
py_aws_utilities-0.0.3.dist-info/METADATA
py_aws_utilities-0.0.3.dist-info/WHEEL
py_aws_utilities-0.0.3.dist-info/top_level.txt
py_aws_utilities-0.0.3.dist-info/RECORD
