Metadata-Version: 2.1
Name: py-aws-utilities
Version: 0.0.3
Summary: Modules and classes for AWS.
Home-page: https://github.com/pypa/sampleproject
Author: J.S. Kroodsma
Author-email: j.s.kroodsma@gmail.com
License: UNKNOWN
Project-URL: Bug Tracker, https://github.com/pypa/sampleproject/issues
Platform: UNKNOWN
Classifier: Programming Language :: Python :: 3
Classifier: License :: OSI Approved :: MIT License
Classifier: Operating System :: OS Independent
Requires-Python: >=3.6
